sch/__init__.py
sch/cli.py
sch/sch.py
tests/__init__.py
tests/test_sch.py
sch2-0.0.2.dist-info/LICENSE
sch2-0.0.2.dist-info/METADATA
sch2-0.0.2.dist-info/WHEEL
sch2-0.0.2.dist-info/entry_points.txt
sch2-0.0.2.dist-info/top_level.txt
sch2-0.0.2.dist-info/RECORD
