Metadata-Version: 2.1
Name: sch2
Version: 0.0.2
Summary: A cron shell wrapper for registering and updating cron jobs automatically in healthchecks
Home-page: https://github.com/enyosolutions-team/health-check-sch.git
Author: Edouard BATIGA
Author-email: dev@enyosolutions.com
License: GNU General Public License v3
Keywords: sch
Platform: UNKNOWN
Classifier: Development Status :: 2 - Pre-Alpha
Classifier: Intended Audience :: Developers
Classifier: License :: OSI Approved :: GNU General Public License v3 (GPLv3)
Classifier: Natural Language :: English
Classifier: Topic :: System :: Monitoring
Classifier: Programming Language :: Python :: 3
Classifier: Programming Language :: Python :: 3.5
Classifier: Programming Language :: Python :: 3.6
Classifier: Programming Language :: Python :: 3.7
Classifier: Programming Language :: Python :: 3.8
Requires-Python: >=3.5
Requires-Dist: arrow
Requires-Dist: click (>=7.0)
Requires-Dist: python-crontab
Requires-Dist: requests
Requires-Dist: configparser
Requires-Dist: tzlocal
